upmath/__init__.py
upmath/lib.py
upmath/src/digits.py
upmath/src/mypi.py
upmath/src/pE.py
upmath/src/psmf.py
upmath/src/upnumber.py
upmath-2.0.0.data/data/LICENSE
upmath-2.0.0.dist-info/LICENSE
upmath-2.0.0.dist-info/METADATA
upmath-2.0.0.dist-info/WHEEL
upmath-2.0.0.dist-info/top_level.txt
upmath-2.0.0.dist-info/RECORD
