Metadata-Version: 2.1
Name: upmath
Version: 2.0.0
Summary: This package creates upnumber (universal precisional number) which can create   flaoting and fractional numbers of bases 2, 8, 10, 16, 32, and 64. That is why, they are   called universal numbers. This number system can create accurate number with any level of   precision set by the user. There are 42 standard math functions for scientific calculations.   So, this package is named as  upmath (universal precision mathematics).
Home-page: 
Author: A K M Aminul Islam
Author-email: aminul71bd@gmail.com
Maintainer: A K M Aminul Islam
Maintainer-email: aminul71bd@gmail.com
License: NEWTONIA FREEWARE LICENSE
License-File: LICENSE
